<?xml version="1.0" encoding="UTF-8"?>
<npc name="Capitã Cristina" script="default.lua" walkinterval="2000" floorchange="0">
    <health now="100" max="100"/>
    <look type="155" head="115" body="114" legs="114" feet="0" addons="3"/>
    <parameters>
        <parameter key="message_greet" value="Olá |PLAYERNAME|, eu vendo alguns poções especiais, diga {troca} ou {trocar}." />
        <parameter key="module_shop" value="1" />
		<parameter key="shop_sellable" value="ferumbras' hat, 5903, 50;" />
		<parameter key="shop_buyable" value="gold coin, 2148, 5000;" />
    </parameters>
</npc>
